docker_export/__init__.py
docker_export-1.1.0.dist-info/METADATA
docker_export-1.1.0.dist-info/WHEEL
docker_export-1.1.0.dist-info/entry_points.txt
docker_export-1.1.0.dist-info/licenses/LICENSE
docker_export-1.1.0.dist-info/RECORD
