Metadata-Version: 2.1
Name: docker-export
Version: 1.1.0
Summary: Export docker image into tar file directly from registry API
Project-URL: Homepage, https://github.com/offspot/docker-export
Project-URL: Donate, https://www.kiwix.org/en/support-us/
Author-email: Kiwix <dev@kiwix.org>
License: GPL-3.0-or-later
License-File: LICENSE
Keywords: docker,image,kiwix,oci
Classifier: License :: OSI Approved :: GNU General Public License v3 or later (GPLv3+)
Classifier: Programming Language :: Python :: 3
Classifier: Programming Language :: Python :: 3.8
Classifier: Programming Language :: Python :: 3.9
Classifier: Programming Language :: Python :: 3.10
Classifier: Programming Language :: Python :: 3.11
Requires-Python: >=3.8
Requires-Dist: pathvalidate==3.2.0
Requires-Dist: requests<3,>=2
Provides-Extra: check
Requires-Dist: pyright==1.1.349; extra == 'check'
Provides-Extra: dev
Requires-Dist: debugpy==1.6.7; extra == 'dev'
Requires-Dist: docker-export[check]; extra == 'dev'
Requires-Dist: docker-export[lint]; extra == 'dev'
Requires-Dist: docker-export[scripts]; extra == 'dev'
Requires-Dist: docker-export[test]; extra == 'dev'
Requires-Dist: docker-export[visual]; extra == 'dev'
Requires-Dist: pre-commit==3.6.0; extra == 'dev'
Provides-Extra: lint
Requires-Dist: black==24.1.1; extra == 'lint'
Requires-Dist: ruff==0.1.15; extra == 'lint'
Provides-Extra: scripts
Requires-Dist: invoke==2.2.0; extra == 'scripts'
Provides-Extra: test
Requires-Dist: coverage==7.4.1; extra == 'test'
Requires-Dist: pytest==8.0.0; extra == 'test'
Provides-Extra: visual
Requires-Dist: humanfriendly>=8.0; extra == 'visual'
Requires-Dist: progressbar2>=4.0; extra == 'visual'
